TracAddHeadersPlugin-0.4.dist-info/METADATA
TracAddHeadersPlugin-0.4.dist-info/RECORD
TracAddHeadersPlugin-0.4.dist-info/WHEEL
TracAddHeadersPlugin-0.4.dist-info/entry_points.txt
TracAddHeadersPlugin-0.4.dist-info/top_level.txt
tracaddheaders/__init__.py
tracaddheaders/plugin.py
