Metadata-Version: 2.1
Name: TracAddHeadersPlugin
Version: 0.4
Summary: AddHeaders Trac Plugin.
Home-page: https://www.trac-hacks.org/wiki/AddHeadersPlugin
Author: Martin Scharrer
Author-email: martin@scharrer-online.de
License: GPLv3
Keywords: trac plugin addheaders
Platform: UNKNOWN
Classifier: Framework :: Trac
Requires-Dist: Trac
